zebrafy/__init__.py
zebrafy/_version.py
zebrafy/crc.py
zebrafy/graphic_field.py
zebrafy/zebrafy_image.py
zebrafy/zebrafy_pdf.py
zebrafy/zebrafy_zpl.py
zebrafy-1.2.2.dist-info/LICENSE.txt
zebrafy-1.2.2.dist-info/METADATA
zebrafy-1.2.2.dist-info/WHEEL
zebrafy-1.2.2.dist-info/top_level.txt
zebrafy-1.2.2.dist-info/RECORD
