Metadata-Version: 2.1
Name: zebrafy
Version: 1.2.2
Summary: Python library for converting PDF and images to Zebra Programming Language (ZPL)
Author-email: Miika Nissi <miika@miikanissi.com>
Maintainer-email: Miika Nissi <miika@miikanissi.com>
License: LGPLv3
Project-URL: Homepage, https://github.com/miikanissi/zebrafy/
Project-URL: Documentation, https://zebrafy.readthedocs.io/
Classifier: Development Status :: 4 - Beta
Classifier: License :: OSI Approved :: GNU Lesser General Public License v3 (LGPLv3)
Classifier: Operating System :: OS Independent
Classifier: Natural Language :: English
Classifier: Programming Language :: Python
Classifier: Programming Language :: Python :: 3.8
Classifier: Programming Language :: Python :: 3.9
Classifier: Programming Language :: Python :: 3.10
Classifier: Programming Language :: Python :: 3.11
Classifier: Programming Language :: Python :: 3.12
Classifier: Intended Audience :: Developers
Classifier: Intended Audience :: System Administrators
Classifier: Intended Audience :: Manufacturing
Classifier: Topic :: Printing
Requires-Python: >=3.8
License-File: LICENSE.txt
Requires-Dist: pillow
Requires-Dist: pypdfium2>=4.8.0
Provides-Extra: docs
Requires-Dist: sphinx>=7.0.0; extra == "docs"
Requires-Dist: sphinx_autodoc_typehints>=2.0.0; extra == "docs"
Requires-Dist: sphinx_rtd_theme>=2.0.0; extra == "docs"
Provides-Extra: test
Requires-Dist: pytest-cov; extra == "test"
Provides-Extra: lint
Requires-Dist: pre-commit; extra == "lint"
Provides-Extra: build
Requires-Dist: setuptools>=64; extra == "build"
Requires-Dist: setuptools_scm>=8; extra == "build"
Requires-Dist: wheel; extra == "build"
Requires-Dist: build; extra == "build"
